{"_id":"65b46c04f1785cf17f42c233","id":"65b46c04f1785cf17f42c233","email":"azad108rahman@gmail.com","firstName":"Azad","lastName":"Rahman","phoneNumber":"15197299645","accountType":"worker","inviteCode":"K83ZJD8C","workerPayMultiplier":1,"createdDate":"2024-01-27T02:35:48.570Z","ipCountryCode":"CA","paypalEmail":"azad108rahman@gmail.com","accountRole":"user","customerReviewEnabled":false,"googleOAuthId":"113689882804676691041","workerSlackId":"U06GS27GQ81","hubstaffUserId":null,"googleClickId":"","acceptedRemoTermsDate":"2024-01-27T02:35:48.380Z","workerStatus":"pending","accountCreditCents":0,"lastOnlineDatetime":"2024-03-04T20:01:41.358Z","lastActive":"2024-03-03T23:47:58.468Z","tieredAssignedProjects":{"bursty":[],"primary":[],"secondary":[],"tertiary":[]},"workerSource":"usqa","teamRole":"admin","canEditTaskTypes":["imageannotation","segmentannotation","textcollection","documenttranscription","namedentityrecognition","videoplaybackannotation","lidarannotation","categorization","multimodaltranscription"],"trainingRewardsEligible":true,"trainingRewardsRequiredEarnings":0,"canAccessLidar":true,"phoneNumberVerified":true,"requiresOnboardingProfiling":true,"onboardingProfilingCompleted":true,"onboardingProfilingWorkerSkillsPending":false,"introCourseCompleted":true,"customerType":"self_service","cachedStats":{"estTotalPayoutCents":543101.4625833333},"preferredTimezone":"utc","successfulLoginAttempts":["2024-02-25T04:14:09.064Z","2024-02-28T07:33:41.959Z","2024-03-02T07:46:18.829Z"],"requiresMfa":false,"verificationStatus":"unverified","activeWorkerTeam":"65da4b76d37f18e3b9d2beba","ageRange":"Twenty-one and older","tags":[{"_id":"5e7ceb6f0806410024bb6b9e","name":"ipcountrycode_CA","createdAt":"2020-03-26T17:50:39.892Z","updatedAt":"2020-03-26T17:50:39.892Z","__v":0},{"_id":"5e7ce9d1bf3120001b4667c8","name":"workersource_tasker","createdAt":"2020-03-26T17:43:45.304Z","updatedAt":"2020-03-26T17:43:45.304Z","__v":0},{"_id":"5e4d3ac61aac39001d47f1ea","name":"allow_all_remotasks_content","createdAt":"2020-02-19T13:40:22.093Z","updatedAt":"2020-02-19T13:40:22.093Z","__v":0},{"_id":"645c2e20c49fe58c66a0f77b","name":"Coder","createdAt":"2023-05-10T23:52:00.203Z","updatedAt":"2023-05-10T23:52:00.203Z","__v":0},{"_id":"6517068a5ed496a571fa0582","name":"tier3_coder_candidate","createdAt":"2023-09-29T17:16:58.420Z","updatedAt":"2023-09-29T17:16:58.420Z","__v":0},{"_id":"65674ac54c7b7afac3d51374","name":"tier3_coder_passed_phone_interview","createdAt":"2023-11-29T14:29:25.468Z","updatedAt":"2023-11-29T14:29:25.468Z","__v":0},{"_id":"655e7bb93e6a5419158fc981","name":"scheduled_coding_live_interview","createdAt":"2023-11-22T22:07:53.310Z","updatedAt":"2023-11-22T22:07:53.310Z","__v":0},{"_id":"655e7bc0c5838fce3b942b84","name":"passed_coding_live_interview","createdAt":"2023-11-22T22:08:00.189Z","updatedAt":"2023-11-22T22:08:00.189Z","__v":0},{"_id":"6556b0a67da97af87c43ccf5","name":"skipped_coding_Screening","createdAt":"2023-11-17T00:15:34.380Z","updatedAt":"2023-11-17T00:15:34.380Z","__v":0},{"_id":"65172efcb0a15238d97bdd59","name":"tier3_coder_US","createdAt":"2023-09-29T20:09:32.792Z","updatedAt":"2023-09-29T20:09:32.792Z","__v":0},{"_id":"64b5b483fd9b74f71fb2dc93","name":"passed_verification","createdAt":"2023-07-17T21:37:07.560Z","updatedAt":"2023-07-17T21:37:07.560Z","__v":0},{"_id":"65b028158e19f5b927486ee0","name":"flamingo_coder_onboarding_all_taskers","createdAt":"2024-01-23T20:56:53.464Z","updatedAt":"2024-01-23T20:56:53.464Z","__v":0},{"_id":"656fca23945efbc027b6c2b7","name":"bee_coders_pre_cert_fail","createdAt":"2023-12-06T01:10:59.703Z","updatedAt":"2023-12-06T01:10:59.703Z","__v":0},{"_id":"6554e724fba79cfd1fb08868","name":"VC_TSM_JimsC","createdAt":"2023-11-15T15:43:32.608Z","updatedAt":"2023-11-15T15:43:32.608Z","__v":0},{"_id":"64de44132c8d71cd2d1a3255","name":"expert_bronze_datascience_US","createdAt":"2023-08-17T16:00:19.284Z","updatedAt":"2023-08-17T16:00:19.284Z","__v":0},{"_id":"65bd33bca2a82ab0b69bd894","name":"platinum_abtest_high","createdAt":"2024-02-02T18:26:04.812Z","updatedAt":"2024-02-02T18:26:04.812Z","__v":0},{"_id":"65d020c61dfc586ebbb03569","name":"passed_code_eval_audit_screening","createdAt":"2024-02-17T02:58:14.881Z","updatedAt":"2024-02-17T02:58:14.881Z","__v":0},{"_id":"65d95bfe07bcfbe5199c4336","name":"depermissioned_from_bulba_code_eval","createdAt":"2024-02-24T03:01:18.134Z","updatedAt":"2024-02-24T03:01:18.134Z","__v":0},{"_id":"65b2ee752fa265ba884ca330","name":"bulb_coders_kaitlynl_pod","createdAt":"2024-01-25T23:27:49.396Z","updatedAt":"2024-01-25T23:27:49.396Z","__v":0},{"_id":"611a9316bb9bdc00186edee5","name":"workersource_usqa","createdAt":"2021-08-16T16:32:22.906Z","updatedAt":"2021-08-16T16:32:22.906Z","__v":0},{"_id":"65557111917859bc8833380d","name":"platinum_tasker_coder","createdAt":"2023-11-16T01:32:01.949Z","updatedAt":"2023-11-16T01:32:01.949Z","__v":0},{"_id":"658b67db197c4dd053541722","name":"ptl_coding_jamesf_pod","metadata":{"payMultiplier":1,"workerId":"655e8c2fbde34d1f3252a594"},"createdAt":"2023-12-26T23:55:07.849Z","updatedAt":"2023-12-26T23:55:07.849Z","__v":0}],"rapidCustomer":false,"disableRapidEmails":false,"studioCustomer":false,"studioSubscriptionTier":"free","remoAdminPersonas":[],"rteInfo":{"reservedHours":0,"hoursTaskedSinceReset":0,"reservedHoursTaskedSinceReset":0,"lastResetTime":"2024-01-27T02:36:40.508Z","unSelectedWorkerTeams":[],"rteTierStatus":"Preferred","_id":"65b46c3817a0cf62fe5a2ac4"},"assignedProjectLayers":[],"lastDismissedAnnouncements":{},"autogenerated":false,"projectGroups":[],"previousStripeCustomerId":"","dotsUserId":"","last2FAPhoneVerificationDate":"2024-01-27T02:36:14.807Z","isPermanent2FABypass":false,"phoneNumberAlphabeticCountryCode":"CA","phoneNumberCallingCountryCode":"1","localPhoneNumber":"5197299645","verifiedCountryCode":"CA","lastPhoneNumberResetDate":"2024-01-27T02:36:14.781Z","smsOptIn":false,"greenHouseResumeLink":"https://grnhse-use1-prod-s5-ghr.s3.amazonaws.com/person_attachments/data/365/455/170/original/Azad_Rahman_2023.pdf?X-Amz-Algorithm=AWS4-HMAC-SHA256&X-Amz-Credential=AKIAVQGOLGY327KJ56ON%2F20240127%2Fus-east-1%2Fs3%2Faws4_request&X-Amz-Date=20240127T023550Z&X-Amz-Expires=604800&X-Amz-SignedHeaders=host&X-Amz-Signature=c105678ae11406bc30c8e9a2cd8d71fa9bb42d11c1d66c1801b3719859a3b256","utmSource":"/en/signup?expert_email=azad108rahman@gmail.com&utm_source=greenhouse&utm_taskerType=Coders&utm_CampaignDescription=tier3_coder_passed_phone_interview&utm_targetcountry=US&utm_targetLanguage=english&utm_owner=recruiting&utm_id=645bf2369f6ba4c4058362e9","hyperwalletUserToken":"","hyperwalletBankAccountToken":"","hyperwalletBankAccount4Digits":"","hyperwalletPaypalToken":"","hyperwalletPaypalEmail":"","genAiTasker":true,"dummyAccountEmails":[],"lastEmptyQueueEvent":{"serverSideRequestId":"4c9f9708-d3bd-493e-8709-f1e7dcad3e3b","userId":"65b46c04f1785cf17f42c233","activeWorkerTeam":"65da4b76d37f18e3b9d2beba","currentPrimaryTeamAssignments":[{"projectId":"65ce92d4fd7f41cbb403edd8"},{"projectId":"65734d8528bda4366f0bb1ca"},{"projectId":"65ce92d4fd7f41cbb403edd8","reviewLevel":-1},{"projectId":"65734d8528bda4366f0bb1ca","reviewLevel":-1},{"projectId":"65cad2da52e77fae2caccc12","reviewLevel":-1}],"currentSecondaryTeamAssignments":[],"emptyQueueReasons":{"65cad2da52e77fae2caccc12":{"-1":"NoTasks"},"65ce92d4fd7f41cbb403edd8":{"allReviewLevels":"NoPermissions"},"65734d8528bda4366f0bb1ca":{"allReviewLevels":"NoPermissions"}},"preAssignmentEmptyQueueReason":null,"requestedAt":"2024-03-04T04:03:15.117Z"},"useSecureResultUrls":false,"customerStatus":"active","ipWhitelist":[],"accessRoles":[],"customerCodeNames":[],"corpRoles":[],"isCorporateUser":false,"__t":"user","hipaa":false,"contracts":[],"activeWorkerTeamId":"65da4b76d37f18e3b9d2beba","activeWorkerTeamName":"Generative AI/Bulba/Code/Code Eval/Rating/Production/Rating/New Code Eval Template","activeWorkerTeamAssignments":[{"projectId":"65ce92d4fd7f41cbb403edd8","tier":"Primary","taskType":"chat","taskCustomer":"6463e58315d308d12ddb5385","projectName":"Bulba Code Eval High Priority","permissionGroup":"65ce92e66aee06b8e4f8d274","inheritedFrom":"Generative AI/Bulba/Code/Code Eval/Rating/Production/Rating/New Code Eval Template","rank":0},{"projectId":"65734d8528bda4366f0bb1ca","tier":"Primary","taskType":"chat","taskCustomer":"6463e58315d308d12ddb5385","projectName":"Bulba Code Eval Rating - Chat task 2.0","permissionGroup":"65734d88ad2410bca2c9ec4d","inheritedFrom":"Generative AI/Bulba/Code/Code Eval/Rating/Production/Rating/New Code Eval Template","rank":1},{"projectId":"65ce92d4fd7f41cbb403edd8","reviewLevel":-1,"tier":"Primary","taskType":"chat","taskCustomer":"6463e58315d308d12ddb5385","projectName":"Bulba Code Eval High Priority","permissionGroup":"65ce92e66aee06b8e4f8d274","inheritedFrom":"Generative AI/Bulba/Code/Code Eval/Rating/Production/Rating/New Code Eval Template","rank":2},{"projectId":"65734d8528bda4366f0bb1ca","reviewLevel":-1,"tier":"Primary","taskType":"chat","taskCustomer":"6463e58315d308d12ddb5385","projectName":"Bulba Code Eval Rating - Chat task 2.0","permissionGroup":"65734d88ad2410bca2c9ec4d","inheritedFrom":"Generative AI/Bulba/Code/Code Eval/Rating/Production/Rating/New Code Eval Template","rank":3},{"projectId":"65cad2da52e77fae2caccc12","reviewLevel":-1,"tier":"Primary","taskType":"chat","taskCustomer":"6463e58315d308d12ddb5385","projectName":"New Code Eval Template","permissionGroup":"65cad2da52e77fae2caccc0b","inheritedFrom":"Generative AI/Bulba/Code/Code Eval/Rating/Production/Rating/New Code Eval Template","rank":4}],"workerTeamProjectPermissions":{"65cad2da52e77fae2caccc12":-1},"assignedProjectLayersProjectPermissions":{},"projectPermissions":{},"projectNames":{},"scaleProfile":{"employmentType":""},"lastIpAddress":"138.229.16.198","currentlyClaimedTasks":[]}
